MF/__init__.py
MF/V3/Buffer.py
MF/V3/Task.py
MF/V3/Three.py
MF/V3/__init__.py
MF/V3/Descriptors/BoundingBox.py
MF/V3/Descriptors/Calibration.py
MF/V3/Descriptors/CaptureImage.py
MF/V3/Descriptors/Export.py
MF/V3/Descriptors/HeatMap.py
MF/V3/Descriptors/Image.py
MF/V3/Descriptors/Import.py
MF/V3/Descriptors/Merge.py
MF/V3/Descriptors/Network.py
MF/V3/Descriptors/Project.py
MF/V3/Descriptors/ProjectActions.py
MF/V3/Descriptors/RemoveVertices.py
MF/V3/Descriptors/ScanData.py
MF/V3/Descriptors/Software.py
MF/V3/Descriptors/System.py
MF/V3/Descriptors/Transform.py
MF/V3/Descriptors/VideoFrame.py
MF/V3/Descriptors/Wifi.py
MF/V3/Descriptors/__init__.py
MF/V3/Descriptors/Settings/Advanced.py
MF/V3/Descriptors/Settings/Camera.py
MF/V3/Descriptors/Settings/Capture.py
MF/V3/Descriptors/Settings/I18n.py
MF/V3/Descriptors/Settings/Projector.py
MF/V3/Descriptors/Settings/Scanner.py
MF/V3/Descriptors/Settings/Software.py
MF/V3/Descriptors/Settings/Style.py
MF/V3/Descriptors/Settings/Turntable.py
MF/V3/Descriptors/Settings/Tutorials.py
MF/V3/Descriptors/Settings/Viewer.py
MF/V3/Descriptors/Settings/__init__.py
MF/V3/Settings/Advanced.py
MF/V3/Settings/Align.py
MF/V3/Settings/AutoFocus.py
MF/V3/Settings/BoundingBox.py
MF/V3/Settings/Camera.py
MF/V3/Settings/Capture.py
MF/V3/Settings/CaptureImage.py
MF/V3/Settings/CopyGroups.py
MF/V3/Settings/CopyProject.py
MF/V3/Settings/Export.py
MF/V3/Settings/Group.py
MF/V3/Settings/HeatMap.py
MF/V3/Settings/I18n.py
MF/V3/Settings/Import.py
MF/V3/Settings/Merge.py
MF/V3/Settings/NewGroup.py
MF/V3/Settings/Project.py
MF/V3/Settings/Projector.py
MF/V3/Settings/Quality.py
MF/V3/Settings/Rectangle.py
MF/V3/Settings/RemoveVertices.py
MF/V3/Settings/Scan.py
MF/V3/Settings/ScanData.py
MF/V3/Settings/ScanSelection.py
MF/V3/Settings/Scanner.py
MF/V3/Settings/Smooth.py
MF/V3/Settings/Software.py
MF/V3/Settings/Style.py
MF/V3/Settings/Turntable.py
MF/V3/Settings/Tutorials.py
MF/V3/Settings/Video.py
MF/V3/Settings/Viewer.py
MF/V3/Settings/Wifi.py
mfthree-11.7.2.dist-info/licenses/LICENSE
mfthree-11.7.2.dist-info/METADATA
mfthree-11.7.2.dist-info/WHEEL
mfthree-11.7.2.dist-info/entry_points.txt
mfthree-11.7.2.dist-info/top_level.txt
mfthree-11.7.2.dist-info/RECORD
