Metadata-Version: 2.4
Name: mfthree
Version: 11.7.2
Summary: Matter and Form - THREE - Library
Project-URL: Homepage, https://github.com/Matter-and-Form/three-python-library
Project-URL: Documentation, https://matter-and-form.github.io/three-python-library/three/scanner.html
Classifier: Programming Language :: Python :: 3
Classifier: Operating System :: OS Independent
Requires-Python: >=3.10
License-File: LICENSE
Requires-Dist: importlib-metadata; python_version < "3.10"
Requires-Dist: protobuf>=5.0.0
Requires-Dist: websocket-client>=1.7.0
Requires-Dist: numpy>=1.26.4
Dynamic: license-file
